sevco_api-0.1.2.dist-info/METADATA
sevco_api-0.1.2.dist-info/WHEEL
sevco_api/__init__.py
sevco_api/__init__.pyi
sevco_api/py.typed
sevco_api/sevco_api.cpython-310-darwin.so
sevco_api-0.1.2.dist-info/RECORD
