Metadata-Version: 2.3
Name: sevco-api
Version: 0.1.2
Classifier: Programming Language :: Rust
Classifier: Programming Language :: Python :: Implementation :: CPython
Classifier: Programming Language :: Python :: Implementation :: PyPy
Summary: Python bindings for the Sevco API
Home-Page: https://www.sevcosecurity.com
License: MIT
Requires-Python: >=3.8
